Metadata-Version: 1.1
Name: glovepy
Version: 0.0.3
Summary: Python implementation of the GloVe algorithm for word embedding
Home-page: https://github.com/umlkhuang/glovepy
Author: Ke Huang
Author-email: khuang@cs.uml.edu
License: MIT
Download-URL: https://github.com/umlkhuang/glovepy
Keywords: NLP,Machine Learning
Platform: linux
Classifier: Intended Audience :: Science/Research
Classifier: Operating System :: OS Independent
Classifier: Programming Language :: Python :: 3.6
